mydata/data.py
yeonghun123-0.0.5.dist-info/METADATA
yeonghun123-0.0.5.dist-info/WHEEL
yeonghun123-0.0.5.dist-info/top_level.txt
yeonghun123-0.0.5.dist-info/RECORD
