Metadata-Version: 2.1
Name: yeonghun123
Version: 0.0.5
Summary: see data
Home-page: https://github.com/chunsejin/calc0001
Download-URL: https://github.com/chunsejin/cal0001
Author: yeonghun
License: UNKNOWN
Platform: UNKNOWN
Classifier: Programming Language :: Python :: 3
Requires-Dist: pandas
Requires-Dist: matplotlib
Requires-Dist: numpy
